{
  "parameters": {
    "OOP": false,
    "CUDA": false,
    "device": "NVIDIA T1000 8GB",
    "model_id": "v0",
    "lr": 0.0005,
    "gamma": 0.95,
    "epsilon_decay": 5000,
    "batch_size": 32,
    "buffer_size": 5000,
    "target_update_freq": 1000
  },
  "runtime": 399.87310791015625,
  "valtime": 143.15443015098572,
  "best_model_at": 4622,
  "val_history": {
    "2690": [
      500.0,
      396.08
    ],
    "2731": [
      454.0,
      399.41
    ],
    "3192": [
      487.0,
      322.92
    ],
    "3204": [
      500.0,
      437.04
    ],
    "3235": [
      500.0,
      475.86
    ],
    "3236": [
      500.0,
      464.18
    ],
    "3270": [
      500.0,
      379.02
    ],
    "3295": [
      487.0,
      491.02
    ],
    "3323": [
      492.0,
      292.13
    ],
    "3350": [
      467.0,
      356.24
    ],
    "3412": [
      500.0,
      352.39
    ],
    "3415": [
      454.0,
      409.54
    ],
    "3427": [
      476.0,
      441.39
    ],
    "3455": [
      452.0,
      485.67
    ],
    "3463": [
      500.0,
      470.48
    ],
    "3472": [
      500.0,
      494.87
    ],
    "3476": [
      477.0,
      460.23
    ],
    "3504": [
      491.0,
      434.98
    ],
    "3511": [
      500.0,
      407.82
    ],
    "3523": [
      500.0,
      442.8
    ],
    "3529": [
      500.0,
      480.75
    ],
    "3624": [
      456.0,
      323.69
    ],
    "3636": [
      500.0,
      280.77
    ],
    "3641": [
      500.0,
      364.33
    ],
    "3642": [
      477.0,
      379.96
    ],
    "3647": [
      462.0,
      346.42
    ],
    "3653": [
      486.0,
      500.0
    ],
    "3701": [
      500.0,
      246.44
    ],
    "3707": [
      500.0,
      284.92
    ],
    "3709": [
      500.0,
      353.14
    ],
    "3713": [
      461.0,
      428.22
    ],
    "3727": [
      500.0,
      496.71
    ],
    "3740": [
      500.0,
      471.24
    ],
    "3962": [
      473.0,
      500.0
    ],
    "3965": [
      500.0,
      500.0
    ],
    "3972": [
      500.0,
      500.0
    ],
    "3973": [
      500.0,
      500.0
    ],
    "3975": [
      500.0,
      500.0
    ],
    "4119": [
      500.0,
      271.27
    ],
    "4121": [
      500.0,
      500.0
    ],
    "4122": [
      500.0,
      500.0
    ],
    "4290": [
      500.0,
      306.15
    ],
    "4293": [
      500.0,
      295.72
    ],
    "4315": [
      481.0,
      236.24
    ],
    "4328": [
      474.0,
      219.02
    ],
    "4370": [
      500.0,
      248.24
    ],
    "4371": [
      500.0,
      272.29
    ],
    "4372": [
      500.0,
      500.0
    ],
    "4374": [
      500.0,
      500.0
    ],
    "4375": [
      500.0,
      283.07
    ],
    "4376": [
      490.0,
      184.73
    ],
    "4388": [
      466.0,
      258.67
    ],
    "4391": [
      500.0,
      233.71
    ],
    "4411": [
      500.0,
      500.0
    ],
    "4413": [
      500.0,
      500.0
    ],
    "4415": [
      500.0,
      365.39
    ],
    "4417": [
      500.0,
      194.18
    ],
    "4419": [
      500.0,
      485.19
    ],
    "4619": [
      451.0,
      435.39
    ],
    "4620": [
      458.0,
      500.0
    ],
    "4621": [
      500.0,
      500.0
    ],
    "4622": [
      500.0,
      499.55
    ]
  },
  "test_result": 499.118
}