{
  "parameters": {
    "OOP": true,
    "CUDA": false,
    "device": "NVIDIA T1000 8GB",
    "model_id": "v1",
    "alpha": 0.0005,
    "gamma": 0.98,
    "beta": 0.005
  },
  "runtime": 98.63630318641663,
  "valtime": 45.03355884552002,
  "best_model_at": 900,
  "val_history": {
    "608": [
      500.0,
      187.4
    ],
    "619": [
      488.0,
      187.95
    ],
    "630": [
      500.0,
      223.45
    ],
    "652": [
      500.0,
      240.1
    ],
    "681": [
      467.0,
      284.4
    ],
    "690": [
      500.0,
      290.65
    ],
    "693": [
      500.0,
      262.95
    ],
    "701": [
      471.0,
      236.75
    ],
    "706": [
      482.0,
      255.05
    ],
    "710": [
      496.0,
      279.45
    ],
    "711": [
      500.0,
      291.85
    ],
    "716": [
      500.0,
      253.95
    ],
    "720": [
      500.0,
      288.45
    ],
    "790": [
      461.0,
      289.95
    ],
    "808": [
      459.0,
      308.5
    ],
    "817": [
      458.0,
      365.95
    ],
    "822": [
      500.0,
      403.05
    ],
    "824": [
      489.0,
      384.95
    ],
    "828": [
      458.0,
      368.5
    ],
    "829": [
      500.0,
      373.5
    ],
    "835": [
      452.0,
      383.8
    ],
    "839": [
      482.0,
      369.55
    ],
    "840": [
      500.0,
      361.2
    ],
    "842": [
      500.0,
      341.85
    ],
    "850": [
      481.0,
      354.55
    ],
    "851": [
      461.0,
      362.2
    ],
    "854": [
      500.0,
      432.95
    ],
    "856": [
      500.0,
      417.6
    ],
    "857": [
      488.0,
      427.45
    ],
    "858": [
      500.0,
      451.9
    ],
    "859": [
      465.0,
      430.75
    ],
    "860": [
      500.0,
      456.35
    ],
    "861": [
      500.0,
      439.55
    ],
    "862": [
      500.0,
      446.5
    ],
    "863": [
      499.0,
      444.25
    ],
    "864": [
      471.0,
      423.7
    ],
    "865": [
      495.0,
      399.45
    ],
    "893": [
      463.0,
      408.6
    ],
    "894": [
      500.0,
      416.65
    ],
    "895": [
      500.0,
      413.65
    ],
    "896": [
      500.0,
      463.15
    ],
    "898": [
      500.0,
      470.1
    ],
    "899": [
      500.0,
      463.3
    ],
    "900": [
      500.0,
      456.3
    ]
  },
  "test_result": 447.932
}