{
  "parameters": {
    "OOP": true,
    "CUDA": false,
    "device": "NVIDIA T1000 8GB",
    "model_id": "v0",
    "lr": 0.0005,
    "gamma": 0.95,
    "epsilon_decay": 5000,
    "batch_size": 32,
    "buffer_size": 5000,
    "target_update_freq": 1000
  },
  "runtime": 220.5240581035614,
  "valtime": 65.53309440612793,
  "best_model_at": 3567,
  "val_history": {
    "2682": [
      500.0,
      385.93
    ],
    "2803": [
      500.0,
      453.11
    ],
    "2835": [
      500.0,
      440.66
    ],
    "2925": [
      500.0,
      498.63
    ],
    "2950": [
      500.0,
      346.48
    ],
    "3114": [
      464.0,
      377.97
    ],
    "3143": [
      500.0,
      499.79
    ],
    "3155": [
      500.0,
      325.69
    ],
    "3179": [
      500.0,
      380.12
    ],
    "3242": [
      500.0,
      319.2
    ],
    "3247": [
      488.0,
      247.15
    ],
    "3495": [
      500.0,
      498.33
    ],
    "3502": [
      500.0,
      500.0
    ],
    "3503": [
      500.0,
      449.63
    ],
    "3507": [
      500.0,
      367.03
    ],
    "3511": [
      500.0,
      269.3
    ],
    "3517": [
      483.0,
      496.18
    ],
    "3551": [
      500.0,
      500.0
    ],
    "3553": [
      500.0,
      500.0
    ],
    "3557": [
      500.0,
      500.0
    ],
    "3562": [
      500.0,
      500.0
    ],
    "3563": [
      500.0,
      500.0
    ],
    "3565": [
      500.0,
      500.0
    ],
    "3566": [
      452.0,
      500.0
    ],
    "3567": [
      500.0,
      500.0
    ]
  },
  "test_result": 500.0
}