{
  "parameters": {
    "OOP": true,
    "CUDA": false,
    "device": "NVIDIA T1000 8GB",
    "model_id": "v0",
    "lr": 0.0005,
    "gamma": 0.95,
    "epsilon_decay": 5000,
    "batch_size": 32,
    "buffer_size": 5000,
    "target_update_freq": 1000
  },
  "runtime": 138.01511693000793,
  "valtime": 20.658106565475464,
  "best_model_at": 4783,
  "val_history": {
    "4741": [
      451.0,
      499.86
    ],
    "4776": [
      500.0,
      356.53
    ],
    "4778": [
      500.0,
      500.0
    ],
    "4783": [
      500.0,
      500.0
    ],
    "4784": [
      456.0,
      436.11
    ],
    "4794": [
      500.0,
      446.23
    ],
    "4811": [
      500.0,
      426.95
    ],
    "4821": [
      462.0,
      488.4
    ]
  },
  "test_result": 500.0
}