{
  "parameters": {
    "OOP": true,
    "CUDA": false,
    "device": "NVIDIA T1000 8GB",
    "model_id": "v0",
    "lr": 0.0005,
    "gamma": 0.95,
    "epsilon_decay": 5000,
    "batch_size": 32,
    "buffer_size": 5000,
    "target_update_freq": 1000
  },
  "runtime": 136.87875247001648,
  "valtime": 35.42037653923035,
  "best_model_at": 3068,
  "val_history": {
    "2953": [
      500.0,
      500.0
    ],
    "2961": [
      500.0,
      500.0
    ],
    "2975": [
      500.0,
      500.0
    ],
    "2976": [
      500.0,
      500.0
    ],
    "2986": [
      500.0,
      500.0
    ],
    "3002": [
      500.0,
      500.0
    ],
    "3005": [
      500.0,
      500.0
    ],
    "3016": [
      500.0,
      387.53
    ],
    "3057": [
      500.0,
      500.0
    ],
    "3066": [
      495.0,
      500.0
    ],
    "3067": [
      500.0,
      500.0
    ],
    "3068": [
      452.0,
      497.29
    ]
  },
  "test_result": 499.818
}