{
  "parameters": {
    "OOP": false,
    "CUDA": false,
    "device": "NVIDIA T1000 8GB",
    "model_id": "v0",
    "lr": 0.0005,
    "gamma": 0.95,
    "epsilon_decay": 5000,
    "batch_size": 32,
    "buffer_size": 5000,
    "target_update_freq": 1000
  },
  "runtime": 574.1514866352081,
  "valtime": 298.3125102519989,
  "best_model_at": 4433,
  "val_history": {
    "2509": [
      450.0,
      340.06
    ],
    "2890": [
      500.0,
      389.78
    ],
    "2978": [
      484.0,
      499.79
    ],
    "2984": [
      500.0,
      343.25
    ],
    "3012": [
      491.0,
      498.88
    ],
    "3029": [
      464.0,
      499.72
    ],
    "3048": [
      469.0,
      500.0
    ],
    "3076": [
      500.0,
      499.91
    ],
    "3099": [
      500.0,
      500.0
    ],
    "3100": [
      500.0,
      500.0
    ],
    "3105": [
      500.0,
      500.0
    ],
    "3110": [
      500.0,
      500.0
    ],
    "3112": [
      482.0,
      500.0
    ],
    "3128": [
      500.0,
      500.0
    ],
    "3139": [
      500.0,
      500.0
    ],
    "3145": [
      500.0,
      500.0
    ],
    "3146": [
      470.0,
      500.0
    ],
    "3163": [
      500.0,
      500.0
    ],
    "3199": [
      500.0,
      311.26
    ],
    "3209": [
      500.0,
      274.15
    ],
    "3239": [
      480.0,
      500.0
    ],
    "3253": [
      500.0,
      500.0
    ],
    "3263": [
      500.0,
      500.0
    ],
    "3276": [
      500.0,
      500.0
    ],
    "3284": [
      478.0,
      500.0
    ],
    "3286": [
      500.0,
      500.0
    ],
    "3287": [
      500.0,
      500.0
    ],
    "3371": [
      500.0,
      500.0
    ],
    "3377": [
      500.0,
      500.0
    ],
    "3383": [
      500.0,
      500.0
    ],
    "3384": [
      500.0,
      500.0
    ],
    "3390": [
      500.0,
      500.0
    ],
    "3393": [
      500.0,
      500.0
    ],
    "3395": [
      481.0,
      500.0
    ],
    "3396": [
      500.0,
      500.0
    ],
    "3400": [
      476.0,
      500.0
    ],
    "3424": [
      500.0,
      500.0
    ],
    "3432": [
      500.0,
      334.56
    ],
    "3443": [
      500.0,
      427.14
    ],
    "3532": [
      471.0,
      499.92
    ],
    "3535": [
      500.0,
      451.51
    ],
    "3539": [
      471.0,
      467.52
    ],
    "3541": [
      500.0,
      500.0
    ],
    "3542": [
      500.0,
      500.0
    ],
    "3546": [
      500.0,
      500.0
    ],
    "3557": [
      500.0,
      500.0
    ],
    "3566": [
      500.0,
      500.0
    ],
    "3601": [
      454.0,
      330.35
    ],
    "3629": [
      452.0,
      474.27
    ],
    "3635": [
      463.0,
      493.95
    ],
    "3649": [
      500.0,
      473.88
    ],
    "3705": [
      477.0,
      465.22
    ],
    "3820": [
      457.0,
      292.84
    ],
    "3839": [
      475.0,
      262.66
    ],
    "3851": [
      500.0,
      263.57
    ],
    "3884": [
      500.0,
      471.65
    ],
    "3888": [
      500.0,
      329.35
    ],
    "3917": [
      454.0,
      178.06
    ],
    "3974": [
      472.0,
      371.69
    ],
    "3976": [
      500.0,
      344.0
    ],
    "4024": [
      500.0,
      477.68
    ],
    "4025": [
      498.0,
      495.54
    ],
    "4034": [
      484.0,
      422.85
    ],
    "4052": [
      500.0,
      488.16
    ],
    "4055": [
      455.0,
      500.0
    ],
    "4057": [
      500.0,
      500.0
    ],
    "4068": [
      500.0,
      499.81
    ],
    "4085": [
      500.0,
      500.0
    ],
    "4092": [
      500.0,
      500.0
    ],
    "4099": [
      500.0,
      500.0
    ],
    "4102": [
      500.0,
      500.0
    ],
    "4112": [
      500.0,
      500.0
    ],
    "4117": [
      500.0,
      500.0
    ],
    "4120": [
      500.0,
      500.0
    ],
    "4138": [
      500.0,
      500.0
    ],
    "4143": [
      500.0,
      500.0
    ],
    "4154": [
      500.0,
      500.0
    ],
    "4165": [
      456.0,
      500.0
    ],
    "4174": [
      500.0,
      500.0
    ],
    "4183": [
      475.0,
      500.0
    ],
    "4186": [
      500.0,
      500.0
    ],
    "4221": [
      500.0,
      500.0
    ],
    "4223": [
      453.0,
      500.0
    ],
    "4233": [
      500.0,
      500.0
    ],
    "4234": [
      500.0,
      500.0
    ],
    "4246": [
      500.0,
      500.0
    ],
    "4250": [
      500.0,
      500.0
    ],
    "4253": [
      500.0,
      500.0
    ],
    "4256": [
      500.0,
      500.0
    ],
    "4258": [
      500.0,
      500.0
    ],
    "4263": [
      500.0,
      500.0
    ],
    "4296": [
      500.0,
      151.84
    ],
    "4311": [
      500.0,
      500.0
    ],
    "4315": [
      500.0,
      500.0
    ],
    "4325": [
      500.0,
      500.0
    ],
    "4333": [
      500.0,
      500.0
    ],
    "4339": [
      500.0,
      500.0
    ],
    "4342": [
      500.0,
      500.0
    ],
    "4345": [
      500.0,
      312.52
    ],
    "4359": [
      500.0,
      500.0
    ],
    "4407": [
      500.0,
      413.69
    ],
    "4416": [
      500.0,
      499.91
    ],
    "4423": [
      500.0,
      375.01
    ],
    "4433": [
      500.0,
      500.0
    ],
    "4441": [
      500.0,
      370.3
    ],
    "4471": [
      468.0,
      443.41
    ],
    "4499": [
      500.0,
      466.22
    ],
    "4508": [
      487.0,
      283.05
    ],
    "4509": [
      500.0,
      391.92
    ],
    "4540": [
      500.0,
      436.16
    ],
    "4724": [
      482.0,
      186.09
    ],
    "4758": [
      500.0,
      332.19
    ],
    "4761": [
      500.0,
      497.99
    ],
    "4865": [
      500.0,
      366.77
    ],
    "4905": [
      500.0,
      115.63
    ],
    "4922": [
      494.0,
      102.52
    ]
  },
  "test_result": 500.0
}