{
  "parameters": {
    "OOP": true,
    "CUDA": false,
    "device": "NVIDIA T1000 8GB",
    "model_id": "v0",
    "lr": 0.0005,
    "gamma": 0.95,
    "epsilon_decay": 5000,
    "batch_size": 32,
    "buffer_size": 5000,
    "target_update_freq": 1000
  },
  "runtime": 138.27131271362305,
  "valtime": 20.7430317401886,
  "best_model_at": 4723,
  "val_history": {
    "4046": [
      500.0,
      90.38
    ],
    "4654": [
      500.0,
      500.0
    ],
    "4659": [
      500.0,
      461.79
    ],
    "4689": [
      500.0,
      93.83
    ],
    "4718": [
      500.0,
      500.0
    ],
    "4723": [
      500.0,
      500.0
    ],
    "4732": [
      452.0,
      479.1
    ],
    "4736": [
      462.0,
      495.55
    ],
    "4905": [
      500.0,
      267.12
    ]
  },
  "test_result": 500.0
}