{
  "parameters": {
    "OOP": false,
    "CUDA": false,
    "device": "NVIDIA T1000 8GB",
    "model_id": "v0",
    "lr": 0.0005,
    "gamma": 0.95,
    "epsilon_decay": 5000,
    "batch_size": 32,
    "buffer_size": 5000,
    "target_update_freq": 1000
  },
  "runtime": 326.92423009872437,
  "valtime": 155.80655312538147,
  "best_model_at": 3630,
  "val_history": {
    "2251": [
      500.0,
      452.46
    ],
    "2382": [
      461.0,
      354.52
    ],
    "2543": [
      499.0,
      296.49
    ],
    "2641": [
      500.0,
      482.81
    ],
    "2791": [
      500.0,
      480.62
    ],
    "2874": [
      500.0,
      293.93
    ],
    "2892": [
      500.0,
      319.89
    ],
    "2900": [
      500.0,
      300.5
    ],
    "3025": [
      493.0,
      378.43
    ],
    "3043": [
      500.0,
      499.95
    ],
    "3077": [
      472.0,
      393.95
    ],
    "3161": [
      499.0,
      347.8
    ],
    "3166": [
      453.0,
      386.72
    ],
    "3175": [
      500.0,
      256.95
    ],
    "3208": [
      500.0,
      455.24
    ],
    "3226": [
      500.0,
      492.04
    ],
    "3322": [
      500.0,
      248.71
    ],
    "3394": [
      500.0,
      404.03
    ],
    "3403": [
      500.0,
      384.77
    ],
    "3414": [
      500.0,
      367.66
    ],
    "3431": [
      500.0,
      476.41
    ],
    "3448": [
      500.0,
      500.0
    ],
    "3453": [
      500.0,
      467.65
    ],
    "3461": [
      500.0,
      497.65
    ],
    "3465": [
      465.0,
      500.0
    ],
    "3474": [
      500.0,
      500.0
    ],
    "3477": [
      472.0,
      500.0
    ],
    "3478": [
      500.0,
      500.0
    ],
    "3483": [
      500.0,
      500.0
    ],
    "3487": [
      500.0,
      500.0
    ],
    "3489": [
      500.0,
      500.0
    ],
    "3491": [
      500.0,
      437.74
    ],
    "3492": [
      500.0,
      500.0
    ],
    "3529": [
      467.0,
      290.64
    ],
    "3539": [
      500.0,
      313.56
    ],
    "3547": [
      500.0,
      384.97
    ],
    "3549": [
      468.0,
      377.58
    ],
    "3553": [
      500.0,
      347.98
    ],
    "3558": [
      465.0,
      467.6
    ],
    "3564": [
      500.0,
      353.73
    ],
    "3565": [
      500.0,
      350.57
    ],
    "3575": [
      465.0,
      387.53
    ],
    "3576": [
      500.0,
      500.0
    ],
    "3580": [
      500.0,
      500.0
    ],
    "3584": [
      500.0,
      500.0
    ],
    "3585": [
      500.0,
      500.0
    ],
    "3589": [
      500.0,
      500.0
    ],
    "3591": [
      500.0,
      500.0
    ],
    "3594": [
      500.0,
      500.0
    ],
    "3595": [
      500.0,
      500.0
    ],
    "3597": [
      491.0,
      500.0
    ],
    "3600": [
      500.0,
      500.0
    ],
    "3603": [
      500.0,
      500.0
    ],
    "3606": [
      500.0,
      500.0
    ],
    "3609": [
      500.0,
      500.0
    ],
    "3617": [
      500.0,
      500.0
    ],
    "3618": [
      454.0,
      500.0
    ],
    "3622": [
      500.0,
      500.0
    ],
    "3626": [
      500.0,
      500.0
    ],
    "3628": [
      500.0,
      500.0
    ],
    "3629": [
      500.0,
      500.0
    ],
    "3630": [
      500.0,
      500.0
    ]
  },
  "test_result": 500.0
}